txsweeper/__init__.py
txsweeper/main.py
txsweeper-0.5.1.dist-info/entry_points.txt
txsweeper-0.5.1.dist-info/WHEEL
txsweeper-0.5.1.dist-info/METADATA
txsweeper-0.5.1.dist-info/RECORD
